{
  "description": "Top 100",
  "monthly": true,
  "results": [
    {
      "wus": 50719535,
      "name": "Anonymous",
      "rank": -1,
      "credit": 1733629103013,
      "team": 0,
      "id": 1437
    },
    {
      "wus": 1597472,
      "name": "NVIDIA_Saturn_V",
      "rank": -1,
      "credit": 283775264652,
      "team": 259918,
      "id": 92215034
    },
    {
      "wus": 913714,
      "name": "Ytl",
      "rank": -1,
      "credit": 73960236930,
      "team": 243328,
      "id": 1754175
    },
    {
      "wus": 931061,
      "name": "ec2spot",
      "rank": -1,
      "credit": 62691932148,
      "team": 238068,
      "id": 71687954
    },
    {
      "wus": 1914407,
      "name": "Arbutus",
      "rank": -1,
      "credit": 44907534401,
      "team": 250396,
      "id": 166229
    },
    {
      "wus": 574114,
      "name": "iomart",
      "rank": -1,
      "credit": 40738478258,
      "team": 240216,
      "id": 68470964
    },
    {
      "wus": 214544,
      "name": "UCB RISE",
      "rank": -1,
      "credit": 35422733083,
      "team": 255460,
      "id": 77406607
    },
    {
      "wus": 229515,
      "name": "GuillaumeSmaha",
      "rank": -1,
      "credit": 34173137888,
      "team": 245993,
      "id": 72827664
    },
    {
      "wus": 157802,
      "name": "hemera_CASUS",
      "rank": -1,
      "credit": 33831709628,
      "team": 258351,
      "id": 104472514
    },
    {
      "wus": 180176,
      "name": "NV-CRF",
      "rank": -1,
      "credit": 33368852312,
      "team": 253515,
      "id": 73385104
    },
    {
      "wus": 168512,
      "name": "84036980",
      "rank": -1,
      "credit": 31865898184,
      "team": 31403,
      "id": 96644
    },
    {
      "wus": 5674159,
      "name": "ANX_Developers",
      "rank": -1,
      "credit": 31263104547,
      "team": 261481,
      "id": 102897045
    },
    {
      "wus": 3612657,
      "name": "CRT-DC_and_Frontier_Labs",
      "rank": -1,
      "credit": 31237710656,
      "team": 711,
      "id": 105067510
    },
    {
      "wus": 219761,
      "name": "Hou5e_ALL_15k84jUoNPb1kodGvYtKDHiBPRX4Qs3kx8",
      "rank": -1,
      "credit": 30551840295,
      "team": 224497,
      "id": 245474
    },
    {
      "wus": 228053,
      "name": "BNL_HPC",
      "rank": -1,
      "credit": 29320727547,
      "team": 262097,
      "id": 109393402
    },
    {
      "wus": 5820804,
      "name": "ATLAS_CPU",
      "rank": -1,
      "credit": 28598208727,
      "team": 38188,
      "id": 90706634
    },
    {
      "wus": 159556,
      "name": "TheWasp",
      "rank": -1,
      "credit": 25488206569,
      "team": 70335,
      "id": 25254
    },
    {
      "wus": 4062832,
      "name": "Multi_Cloud_Galaxy",
      "rank": -1,
      "credit": 22964065244,
      "team": 229957,
      "id": 76142767
    },
    {
      "wus": 133301,
      "name": "tnt.uni-hannover.de",
      "rank": -1,
      "credit": 20300858413,
      "team": 127907,
      "id": 102846155
    },
    {
      "wus": 3744486,
      "name": "CMS-Experiment",
      "rank": -1,
      "credit": 20197317442,
      "team": 38188,
      "id": 79847386
    },
    {
      "wus": 117102,
      "name": "Catalina588_ALL_1EMQiByPxuaffjHVyb4RDLXChMkwgWmYUn",
      "rank": -1,
      "credit": 19766942669,
      "team": 224497,
      "id": 335125
    },
    {
      "wus": 1203767,
      "name": "UART_Puma_0_Rome_0",
      "rank": -1,
      "credit": 19387835654,
      "team": 239945,
      "id": 112148086
    },
    {
      "wus": 519549,
      "name": "criteo",
      "rank": -1,
      "credit": 18474561931,
      "team": 0,
      "id": 69467797
    },
    {
      "wus": 1194295,
      "name": "sdumont.petrobras",
      "rank": -1,
      "credit": 17529613671,
      "team": 247463,
      "id": 72635396
    },
    {
      "wus": 505358,
      "name": "raplab",
      "rank": -1,
      "credit": 17438042560,
      "team": 259918,
      "id": 125840509
    },
    {
      "wus": 840858,
      "name": "blspcy",
      "rank": -1,
      "credit": 17423411014,
      "team": 266168,
      "id": 207491045
    },
    {
      "wus": 404993,
      "name": "hemera",
      "rank": -1,
      "credit": 17395393681,
      "team": 258351,
      "id": 83837941
    },
    {
      "wus": 74984,
      "name": "CDCTResearchAndInnovationHubs",
      "rank": -1,
      "credit": 16620376163,
      "team": 237712,
      "id": 69347523
    },
    {
      "wus": 232276,
      "name": "cedar",
      "rank": -1,
      "credit": 16287271679,
      "team": 250396,
      "id": 199445
    },
    {
      "wus": 99805,
      "name": "knopflerbruce",
      "rank": -1,
      "credit": 15394675013,
      "team": 37651,
      "id": 13857
    },
    {
      "wus": 921282,
      "name": "Kevin_Day",
      "rank": -1,
      "credit": 15384100848,
      "team": 256378,
      "id": 98476877
    },
    {
      "wus": 1575376,
      "name": "Intel_Diamond",
      "rank": -1,
      "credit": 14982981445,
      "team": 711,
      "id": 119446933
    },
    {
      "wus": 112100,
      "name": "CUREfor_ALL_1forCUREZnmiUxGQ7qwjJ7AijUmPxt4LV",
      "rank": -1,
      "credit": 14954357389,
      "team": 224497,
      "id": 259585
    },
    {
      "wus": 84274,
      "name": "Kjetil_Lura",
      "rank": -1,
      "credit": 13680778680,
      "team": 37651,
      "id": 13773
    },
    {
      "wus": 110164,
      "name": "DESY-ZN_GPU",
      "rank": -1,
      "credit": 13395785755,
      "team": 38188,
      "id": 160053867
    },
    {
      "wus": 88714,
      "name": "pchung",
      "rank": -1,
      "credit": 13169546869,
      "team": 242705,
      "id": 1522838
    },
    {
      "wus": 102897,
      "name": "war",
      "rank": -1,
      "credit": 13045664927,
      "team": 37651,
      "id": 27111
    },
    {
      "wus": 89993,
      "name": "CAVE2",
      "rank": -1,
      "credit": 12126171189,
      "team": 263148,
      "id": 118240225
    },
    {
      "wus": 257181,
      "name": "ctTEAM",
      "rank": -1,
      "credit": 12020179734,
      "team": 251999,
      "id": 74512365
    },
    {
      "wus": 716031,
      "name": "Dapper_Sandstorm",
      "rank": -1,
      "credit": 11565053082,
      "team": 257579,
      "id": 81172866
    },
    {
      "wus": 194333,
      "name": "Principled_Technologies",
      "rank": -1,
      "credit": 11245322690,
      "team": 0,
      "id": 72279837
    },
    {
      "wus": 50926,
      "name": "flexential_nvidia_dgx",
      "rank": -1,
      "credit": 11158327783,
      "team": 251259,
      "id": 82715878
    },
    {
      "wus": 104272,
      "name": "tralph",
      "rank": -1,
      "credit": 10931713926,
      "team": 52737,
      "id": 69384825
    },
    {
      "wus": 368858,
      "name": "Stefan_Gerlach",
      "rank": -1,
      "credit": 10876795389,
      "team": 251386,
      "id": 73950295
    },
    {
      "wus": 93869,
      "name": "HayesK_ALL_18SjyNbF8VdXaNAFCVfG4rAHUyvtdmoFvX",
      "rank": -1,
      "credit": 10833251551,
      "team": 32,
      "id": 335566
    },
    {
      "wus": 92068,
      "name": "COMPaaS",
      "rank": -1,
      "credit": 10579854553,
      "team": 263148,
      "id": 124551136
    },
    {
      "wus": 270255,
      "name": "Farnarkle",
      "rank": -1,
      "credit": 10368776799,
      "team": 253919,
      "id": 79672739
    },
    {
      "wus": 72627,
      "name": "TML_ALL_1Fb7XpTZN9gefApL87L51CY34aT7DZKCUu",
      "rank": -1,
      "credit": 9339953627,
      "team": 224497,
      "id": 265852
    },
    {
      "wus": 105545,
      "name": "mharsch",
      "rank": -1,
      "credit": 9327105024,
      "team": 0,
      "id": 195453
    },
    {
      "wus": 776581,
      "name": "ALICE-FLP",
      "rank": -1,
      "credit": 9086452172,
      "team": 38188,
      "id": 95514355
    },
    {
      "wus": 41536,
      "name": "Nvidia_SA_Team",
      "rank": -1,
      "credit": 9070113200,
      "team": 259918,
      "id": 180838429
    },
    {
      "wus": 312748,
      "name": "FCE_CTU",
      "rank": -1,
      "credit": 9032599320,
      "team": 252064,
      "id": 183999339
    },
    {
      "wus": 54416,
      "name": "Mark_F_Williams",
      "rank": -1,
      "credit": 9014322449,
      "team": 198,
      "id": 15758
    },
    {
      "wus": 50761,
      "name": "legendarypoet",
      "rank": -1,
      "credit": 8631357071,
      "team": 223518,
      "id": 333091
    },
    {
      "wus": 36731,
      "name": "ics_dsnlp",
      "rank": -1,
      "credit": 8267562889,
      "team": 0,
      "id": 109233102
    },
    {
      "wus": 47509,
      "name": "NetAppAI",
      "rank": -1,
      "credit": 8222178722,
      "team": 36152,
      "id": 76228711
    },
    {
      "wus": 69549,
      "name": "1%_china",
      "rank": -1,
      "credit": 8194544350,
      "team": 3213,
      "id": 257909
    },
    {
      "wus": 95809,
      "name": "MightyMayfield",
      "rank": -1,
      "credit": 7823041246,
      "team": 257944,
      "id": 85831522
    },
    {
      "wus": 147133,
      "name": "ogbon.petrobras",
      "rank": -1,
      "credit": 7822566378,
      "team": 247463,
      "id": 73251093
    },
    {
      "wus": 91039,
      "name": "BulgarDemon",
      "rank": -1,
      "credit": 7741654974,
      "team": 224497,
      "id": 98767
    },
    {
      "wus": 42751,
      "name": "Pokey_TA",
      "rank": -1,
      "credit": 7697151361,
      "team": 198,
      "id": 19925
    },
    {
      "wus": 73527,
      "name": "Justin_Blau",
      "rank": -1,
      "credit": 7459272347,
      "team": 242705,
      "id": 69239383
    },
    {
      "wus": 49959,
      "name": "V_ALL_18UvasjLebgbreGp5KqwL1RHU7WWXFT7mC",
      "rank": -1,
      "credit": 7354173104,
      "team": 224497,
      "id": 80355459
    },
    {
      "wus": 37083,
      "name": "BadBertie",
      "rank": -1,
      "credit": 6766626625,
      "team": 111065,
      "id": 97898
    },
    {
      "wus": 53292,
      "name": "inder372",
      "rank": -1,
      "credit": 6707747367,
      "team": 111065,
      "id": 11315
    },
    {
      "wus": 325037,
      "name": "Jasminl",
      "rank": -1,
      "credit": 6406983957,
      "team": 51,
      "id": 173048
    },
    {
      "wus": 744601,
      "name": "CAPTAIN_VSAN",
      "rank": -1,
      "credit": 6374758824,
      "team": 52737,
      "id": 74974140
    },
    {
      "wus": 537753,
      "name": "novosirj",
      "rank": -1,
      "credit": 6344250456,
      "team": 86926,
      "id": 68113902
    },
    {
      "wus": 94418,
      "name": "HayesK_ALL_18SjyNbF8VdXaNAFCVfG4rAHUyvtdmoFvX",
      "rank": -1,
      "credit": 6255401142,
      "team": 224497,
      "id": 335566
    },
    {
      "wus": 36996,
      "name": "mame63",
      "rank": -1,
      "credit": 6000159926,
      "team": 86565,
      "id": 15575
    },
    {
      "wus": 43926,
      "name": "gordonbb",
      "rank": -1,
      "credit": 5911253756,
      "team": 223518,
      "id": 348895
    },
    {
      "wus": 316499,
      "name": "RHRK",
      "rank": -1,
      "credit": 5822393515,
      "team": 235935,
      "id": 61977515
    },
    {
      "wus": 194208,
      "name": "MineAllMine_ALL_1J4dCchuCPe4VKo8CGYKRLJPxZNRcmnTF1",
      "rank": -1,
      "credit": 5781443165,
      "team": 224497,
      "id": 263139
    },
    {
      "wus": 35765,
      "name": "CoolGTX",
      "rank": -1,
      "credit": 5675308777,
      "team": 111065,
      "id": 259460
    },
    {
      "wus": 334468,
      "name": "PXD_TS",
      "rank": -1,
      "credit": 5632941134,
      "team": 258837,
      "id": 86035005
    },
    {
      "wus": 39898,
      "name": "g-unit123",
      "rank": -1,
      "credit": 5587150228,
      "team": 240111,
      "id": 69208278
    },
    {
      "wus": 29003,
      "name": "Keyco",
      "rank": -1,
      "credit": 5565082281,
      "team": 3213,
      "id": 325042
    },
    {
      "wus": 24032,
      "name": "efraim",
      "rank": -1,
      "credit": 5502760157,
      "team": 0,
      "id": 1075076
    },
    {
      "wus": 154488,
      "name": "Threader_CPF",
      "rank": -1,
      "credit": 5387863605,
      "team": 254500,
      "id": 79381202
    },
    {
      "wus": 73291,
      "name": "Z4G4",
      "rank": -1,
      "credit": 5321160278,
      "team": 265163,
      "id": 195223751
    },
    {
      "wus": 42114,
      "name": "WhitehawkEQ",
      "rank": -1,
      "credit": 5209930666,
      "team": 32,
      "id": 113131
    },
    {
      "wus": 28950,
      "name": "Scott",
      "rank": -1,
      "credit": 5190379905,
      "team": 41608,
      "id": 22266
    },
    {
      "wus": 36243,
      "name": "Shirty",
      "rank": -1,
      "credit": 5113727729,
      "team": 35947,
      "id": 22779
    },
    {
      "wus": 4621432,
      "name": "Anonymous",
      "rank": -1,
      "credit": 5049876626,
      "team": 258507,
      "id": 1437
    },
    {
      "wus": 80801,
      "name": "davy",
      "rank": -1,
      "credit": 5048152854,
      "team": 237170,
      "id": 6018
    },
    {
      "wus": 28398,
      "name": "MrMoo",
      "rank": -1,
      "credit": 5032670536,
      "team": 224497,
      "id": 263323
    },
    {
      "wus": 43282,
      "name": "PFITS_ALL_18ahXU3GWiadQ4L2j9qAK17ounUgwdpyoB",
      "rank": -1,
      "credit": 4959238351,
      "team": 224497,
      "id": 336184
    },
    {
      "wus": 414904,
      "name": "HPE_EPC_DCS_CIC",
      "rank": -1,
      "credit": 4896115356,
      "team": 247332,
      "id": 89535223
    },
    {
      "wus": 35343,
      "name": "surfsara",
      "rank": -1,
      "credit": 4887227813,
      "team": 242482,
      "id": 69677848
    },
    {
      "wus": 212961,
      "name": "ACC4",
      "rank": -1,
      "credit": 4865514451,
      "team": 254839,
      "id": 76660911
    },
    {
      "wus": 40514,
      "name": "msi_TW",
      "rank": -1,
      "credit": 4851116411,
      "team": 31403,
      "id": 107161
    },
    {
      "wus": 614017,
      "name": "LHCbHLT",
      "rank": -1,
      "credit": 4813610672,
      "team": 38188,
      "id": 108172736
    },
    {
      "wus": 182407,
      "name": "ICT_CTU",
      "rank": -1,
      "credit": 4658493644,
      "team": 245800,
      "id": 68756756
    },
    {
      "wus": 35588,
      "name": "DocJonz",
      "rank": -1,
      "credit": 4647901542,
      "team": 35947,
      "id": 6780
    },
    {
      "wus": 50086,
      "name": "Jedd_bag",
      "rank": -1,
      "credit": 4643946264,
      "team": 11108,
      "id": 12048
    },
    {
      "wus": 346649,
      "name": "the901",
      "rank": -1,
      "credit": 4581070320,
      "team": 33,
      "id": 420077
    },
    {
      "wus": 78581,
      "name": "ICT_Systems_Laboratory,_Fujitsu_Laboratories_Ltd.",
      "rank": -1,
      "credit": 4550511976,
      "team": 259660,
      "id": 130381216
    },
    {
      "wus": 41964,
      "name": "rickoic",
      "rank": -1,
      "credit": 4536956610,
      "team": 15,
      "id": 21165
    },
    {
      "wus": 59369,
      "name": "SwitchDK",
      "rank": -1,
      "credit": 4461450067,
      "team": 266452,
      "id": 495933
    },
    {
      "wus": 157987,
      "name": "AustinEventsWarehouse",
      "rank": -1,
      "credit": 4424851250,
      "team": 257967,
      "id": 81585253
    }
  ],
  "month": 12,
  "year": 2020,
  "query": "donor",
  "path": "donors-monthly"
}
